wtformsblacksheep/__init__.py
wtformsblacksheep/form.py
WTFormsBlacksheep-0.0.2.dist-info/LICENCE.txt
WTFormsBlacksheep-0.0.2.dist-info/METADATA
WTFormsBlacksheep-0.0.2.dist-info/WHEEL
WTFormsBlacksheep-0.0.2.dist-info/top_level.txt
WTFormsBlacksheep-0.0.2.dist-info/RECORD
