Metadata-Version: 2.1
Name: WTFormsBlacksheep
Version: 0.0.2
Summary: WTForm Blacksheep
Home-page: 
Author: Abdulaminhon Khaydarov
Author-email: info@thinkland.uz
License: MIT
Keywords: wtformsblacksheep
Platform: UNKNOWN
Classifier: License :: OSI Approved :: MIT License
Classifier: Programming Language :: Python :: 3
Classifier: Programming Language :: Python :: 3.9
License-File: LICENCE.txt
Requires-Dist: WTForms
Requires-Dist: blacksheep
Requires-Dist: multidict
Requires-Dist: pydantic
